Metadata-Version: 2.1
Name: reconchess
Version: 1.6.9
Summary: A python package for building Reconnaissance Chess players
Home-page: https://github.com/reconnaissanceblindchess/reconchess
Author: Johns Hopkins University Applied Physics Laboratory
License: UNKNOWN
Project-URL: Documentation, https://reconchess.readthedocs.io/en/latest/index.html
Project-URL: Source, https://github.com/reconnaissanceblindchess/reconchess
Project-URL: Tracker, https://github.com/reconnaissanceblindchess/reconchess/issues
Platform: UNKNOWN
Classifier: Programming Language :: Python :: 3.5
Classifier: Programming Language :: Python :: 3.6
Classifier: Programming Language :: Python :: 3.7
Classifier: Programming Language :: Python :: 3.8
Classifier: License :: OSI Approved :: BSD License
Classifier: Operating System :: OS Independent
Classifier: Topic :: Games/Entertainment :: Board Games
Classifier: Topic :: Scientific/Engineering :: Artificial Intelligence
Classifier: Topic :: Software Development :: Libraries
Requires-Python: >=3.5
License-File: LICENSE
